plp/__init__.py
plp/download.py
plp/eventrefparser.py
plp/eventsignature.py
plp/ordinal.py
plp/parsing.py
plp/signature.py
plp/resources/acronyms.yaml
plp/resources/cityNamePrefixes.yaml
plp/resources/cityNames.yaml
plp/resources/countries.yaml
plp/resources/dictionary.yaml
plp/resources/years.yaml
pylookupparser-0.0.2.dist-info/METADATA
pylookupparser-0.0.2.dist-info/WHEEL
pylookupparser-0.0.2.dist-info/licenses/LICENSE
pylookupparser-0.0.2.dist-info/RECORD
