Metadata-Version: 2.1
Name: pyLookupParser
Version: 0.0.2
Project-URL: Home, https://github.com/WolfgangFahl/pyLookupParser
Project-URL: Documentation, https://wiki.bitplan.com/index.php/pyLookupParser
Project-URL: Source, https://github.com/WolfgangFahl/pyLookupParser
Author-email: Wolfgang Fahl <wf@bitplan.com>, Tim Holzheim <tim.holzheim@rwth-aachen.de>
Maintainer-email: Wolfgang Fahl <wf@bitplan.com>
License-File: LICENSE
Classifier: Development Status :: 4 - Beta
Classifier: Environment :: Web Environment
Classifier: Intended Audience :: Developers
Classifier: Intended Audience :: Education
Classifier: Intended Audience :: Science/Research
Classifier: License :: OSI Approved :: Apache Software License
Classifier: Operating System :: OS Independent
Classifier: Programming Language :: Python :: 3 :: Only
Classifier: Programming Language :: Python :: 3.8
Classifier: Programming Language :: Python :: 3.9
Classifier: Programming Language :: Python :: 3.10
Classifier: Programming Language :: Python :: 3.11
Classifier: Topic :: Software Development :: User Interfaces
Requires-Python: >=3.8
Requires-Dist: num2words>=0.5.9
Requires-Dist: pylodstorage>=0.4.9
Requires-Dist: pyparsing>=3.0.9
Provides-Extra: test
Requires-Dist: green; extra == 'test'
